hktvtrack/__init__.py
hktvtrack/track.py
hktvtrack-0.0.2.dist-info/METADATA
hktvtrack-0.0.2.dist-info/WHEEL
hktvtrack-0.0.2.dist-info/top_level.txt
hktvtrack-0.0.2.dist-info/RECORD
