Metadata-Version: 2.1
Name: hktvtrack
Version: 0.0.2
Summary: HktvTrack
Home-page: UNKNOWN
Author: fung
Author-email: fung20052006@gmail.com
License: UNKNOWN
Platform: UNKNOWN
Classifier: Programming Language :: Python :: 2.7
Classifier: License :: OSI Approved :: MIT License
Classifier: Operating System :: OS Independent
Requires-Python: >=2.7
Requires-Dist: beautifulsoup4
